{
    "data_name": "DOF6PlaneQuat10_rU&0_Fs20_dt0.01_100K",
    "network": "deina_sd",
    "enc_x_shape": [
        10,
        100,
        100,
        10
    ],
    "enc_u_shape": [
        4,
        50,
        50,
        4
    ],
    "aux_shape": [
        -1,
        50,
        50,
        -1
    ],
    "activation": "hrelu",
    "task_head": "dof6_10",
    "description": "",
    "weights_name": "/model.pt",
    "epochs": 200,
    "batch_size": 128,
    "lr": 0.01,
    "lr_sch_step": 50,
    "lr_sch_gamma": 0.618,
    "weight_decay": 0,
    "device": "cuda",
    "seed": 10,
    "train": true,
    "val_feq": 4,
    "n_shifts": 51,
    "use_rbf": false,
    "enc_rbf": false,
    "use_enc_x": true,
    "use_enc_u": false,
    "use_complex": true,
    "use_affine": false,
    "kernel": "gaussian",
    "drop_prob": 0.0,
    "lw_state": 1.0,
    "lw_latent": 1.0,
    "lw_x_inf_2": 0.1,
    "lw_h_inf_2": 0.1,
    "lw_l1reg": 0,
    "lw_l2reg": 0.001,
    "use_huber": true,
    "verbose": true,
    "viz": true,
    "viz_random": false,
    "viz_gui": false,
    "viz_save_itr": false,
    "viz_phase_x_idx": 0,
    "viz_phase_y_idx": 1,
    "use_floyd": false
}